clouddrift/__init__.py
clouddrift/_version.py
clouddrift/binning.py
clouddrift/datasets.py
clouddrift/kinematics.py
clouddrift/pairs.py
clouddrift/plotting.py
clouddrift/ragged.py
clouddrift/raggedarray.py
clouddrift/signal.py
clouddrift/sphere.py
clouddrift/transfer.py
clouddrift/wavelet.py
clouddrift/adapters/__init__.py
clouddrift/adapters/andro.py
clouddrift/adapters/glad.py
clouddrift/adapters/hurdat2.py
clouddrift/adapters/ibtracs.py
clouddrift/adapters/mosaic.py
clouddrift/adapters/subsurface_floats.py
clouddrift/adapters/utils.py
clouddrift/adapters/yomaha.py
clouddrift/adapters/gdp/__init__.py
clouddrift/adapters/gdp/gdp1h.py
clouddrift/adapters/gdp/gdp6h.py
clouddrift/adapters/gdp/gdpsource.py
clouddrift-0.46.0.dist-info/METADATA
clouddrift-0.46.0.dist-info/WHEEL
clouddrift-0.46.0.dist-info/licenses/LICENSE
clouddrift-0.46.0.dist-info/RECORD
