Metadata-Version: 2.4
Name: clouddrift
Version: 0.46.0
Summary: Accelerating the use of Lagrangian data for atmospheric, oceanic, and climate sciences
Project-URL: Homepage, https://github.com/Cloud-Drift/clouddrift
Project-URL: Documentation, https://cloud-drift.github.io/clouddrift
Author-email: Shane Elipot <selipot@miami.edu>, Philippe Miron <philippemiron@gmail.com>, Milan Curcic <mcurcic@miami.edu>, Kevin Santana <kevinsantana11@gmail.com>, Kevin Shuman <kxs5046@miami.edu>
License-File: LICENSE
Classifier: License :: OSI Approved :: MIT License
Classifier: Operating System :: OS Independent
Classifier: Programming Language :: Python :: 3
Requires-Python: >=3.10
Requires-Dist: aiohttp>=3.8.4
Requires-Dist: awkward>=2.0.0
Requires-Dist: fsspec>=2022.3.0
Requires-Dist: h5netcdf>=1.3.0
Requires-Dist: netcdf4>=1.6.4
Requires-Dist: numpy>=1.22.4
Requires-Dist: pandas>=1.3.4
Requires-Dist: pyarrow>=8.0.0
Requires-Dist: requests>=2.31.0
Requires-Dist: scipy>=1.11.2
Requires-Dist: tenacity>=8.2.3
Requires-Dist: tqdm>=4.64.0
Requires-Dist: xarray>=2023.5.0
Requires-Dist: zarr<3,>=2.14.2
Provides-Extra: all
Requires-Dist: build; extra == 'all'
Requires-Dist: cartopy; extra == 'all'
Requires-Dist: coverage; extra == 'all'
Requires-Dist: docutils; extra == 'all'
Requires-Dist: ipykernel; extra == 'all'
Requires-Dist: matplotlib; extra == 'all'
Requires-Dist: mypy; extra == 'all'
Requires-Dist: pytest; extra == 'all'
Requires-Dist: ruff; extra == 'all'
Requires-Dist: sphinx; extra == 'all'
Requires-Dist: sphinx-book-theme; extra == 'all'
Requires-Dist: sphinx-copybutton; extra == 'all'
Requires-Dist: twine; extra == 'all'
Provides-Extra: dev
Requires-Dist: build; extra == 'dev'
Requires-Dist: coverage; extra == 'dev'
Requires-Dist: docutils; extra == 'dev'
Requires-Dist: ipykernel; extra == 'dev'
Requires-Dist: mypy; extra == 'dev'
Requires-Dist: pytest; extra == 'dev'
Requires-Dist: ruff; extra == 'dev'
Requires-Dist: twine; extra == 'dev'
Provides-Extra: docs
Requires-Dist: sphinx; extra == 'docs'
Requires-Dist: sphinx-book-theme; extra == 'docs'
Requires-Dist: sphinx-copybutton; extra == 'docs'
Provides-Extra: plotting
Requires-Dist: cartopy; extra == 'plotting'
Requires-Dist: matplotlib; extra == 'plotting'
